{
  "Sayu_SkillUpgrade_1": [
    {
      "abilityName": "Avatar_Sayu_NormalAttack_DamageHandler",
      "IIKDOHHIDNM": "NormalAttack_01_DamagePercentage",
      "CIKHACMMGOL": {
        "MIJEEBIEOCG": "%1"
      },
      "BBIKFMELLKH": {
        "MIJEEBIEOCG": 0
      }
    },
    {
      "abilityName": "Avatar_Sayu_NormalAttack_DamageHandler",
      "IIKDOHHIDNM": "NormalAttack_02_DamagePercentage",
      "CIKHACMMGOL": {
        "MIJEEBIEOCG": "%2"
      },
      "BBIKFMELLKH": {
        "MIJEEBIEOCG": 0
      }
    },
    {
      "abilityName": "Avatar_Sayu_NormalAttack_DamageHandler",
      "IIKDOHHIDNM": "NormalAttack_03_1_DamagePercentage",
      "CIKHACMMGOL": {
        "MIJEEBIEOCG": "%3"
      },
      "BBIKFMELLKH": {
        "MIJEEBIEOCG": 0
      }
    },
    {
      "abilityName": "Avatar_Sayu_NormalAttack_DamageHandler",
      "IIKDOHHIDNM": "NormalAttack_03_2_DamagePercentage",
      "CIKHACMMGOL": {
        "MIJEEBIEOCG": "%4"
      },
      "BBIKFMELLKH": {
        "MIJEEBIEOCG": 0
      }
    },
    {
      "abilityName": "Avatar_Sayu_NormalAttack_DamageHandler",
      "IIKDOHHIDNM": "NormalAttack_04_DamagePercentage",
      "CIKHACMMGOL": {
        "MIJEEBIEOCG": "%5"
      },
      "BBIKFMELLKH": {
        "MIJEEBIEOCG": 0
      }
    },
    {
      "abilityName": "Avatar_Sayu_NormalAttack_DamageHandler",
      "IIKDOHHIDNM": "ExtraAttack_1_DamagePercentage",
      "CIKHACMMGOL": {
        "MIJEEBIEOCG": "%6"
      },
      "BBIKFMELLKH": {
        "MIJEEBIEOCG": 0
      }
    },
    {
      "abilityName": "Avatar_Sayu_NormalAttack_DamageHandler",
      "IIKDOHHIDNM": "ExtraAttack_2_DamagePercentage",
      "CIKHACMMGOL": {
        "MIJEEBIEOCG": "%7"
      },
      "BBIKFMELLKH": {
        "MIJEEBIEOCG": 0
      }
    },
    {
      "abilityName": "Avatar_Sayu_ExtraAttack",
      "IIKDOHHIDNM": "ExtraAttack_Claymore_Stamina_Cost",
      "CIKHACMMGOL": {
        "MIJEEBIEOCG": "%8"
      },
      "BBIKFMELLKH": {
        "MIJEEBIEOCG": 0
      }
    },
    {
      "abilityName": "Avatar_Sayu_ExtraAttack",
      "IIKDOHHIDNM": "ExtraAttack_Claymore_MaxTime",
      "CIKHACMMGOL": {
        "MIJEEBIEOCG": "%9"
      },
      "BBIKFMELLKH": {
        "MIJEEBIEOCG": 0
      }
    },
    {
      "abilityName": "Avatar_Sayu_FallingAnthem",
      "IIKDOHHIDNM": "FallingAnthem_Normal_Loop_Damage",
      "CIKHACMMGOL": {
        "MIJEEBIEOCG": "%10"
      },
      "BBIKFMELLKH": {
        "MIJEEBIEOCG": 0
      }
    },
    {
      "abilityName": "Avatar_Sayu_FallingAnthem",
      "IIKDOHHIDNM": "FallingAnthem_Normal_Rank_1_Damage",
      "CIKHACMMGOL": {
        "MIJEEBIEOCG": "%11"
      },
      "BBIKFMELLKH": {
        "MIJEEBIEOCG": 0
      }
    },
    {
      "abilityName": "Avatar_Sayu_FallingAnthem",
      "IIKDOHHIDNM": "FallingAnthem_Normal_Rank_2_Damage",
      "CIKHACMMGOL": {
        "MIJEEBIEOCG": "%12"
      },
      "BBIKFMELLKH": {
        "MIJEEBIEOCG": 0
      }
    }
  ],
  "Sayu_SkillUpgrade_2": [
    {
      "abilityName": "Avatar_Sayu_ElementalArt_Bullet",
      "IIKDOHHIDNM": "Roll_Damage",
      "CIKHACMMGOL": {
        "MIJEEBIEOCG": "%1"
      },
      "BBIKFMELLKH": {
        "MIJEEBIEOCG": 0
      }
    },
    {
      "abilityName": "Avatar_Sayu_ElementalArt_Roll_Bullet",
      "IIKDOHHIDNM": "Roll_Damage",
      "CIKHACMMGOL": {
        "MIJEEBIEOCG": "%1"
      },
      "BBIKFMELLKH": {
        "MIJEEBIEOCG": 0
      }
    },
    {
      "abilityName": "Avatar_Sayu_ElementalArt_Roll_Bullet",
      "IIKDOHHIDNM": "MixRoll_Damage",
      "CIKHACMMGOL": {
        "MIJEEBIEOCG": "%2"
      },
      "BBIKFMELLKH": {
        "MIJEEBIEOCG": 0
      }
    },
    {
      "abilityName": "Avatar_Sayu_ElementalArt_Click",
      "IIKDOHHIDNM": "Click_StrikeDamage",
      "CIKHACMMGOL": {
        "MIJEEBIEOCG": "%3"
      },
      "BBIKFMELLKH": {
        "MIJEEBIEOCG": 0
      }
    },
    {
      "abilityName": "Avatar_Sayu_ElementalArt_Hold",
      "IIKDOHHIDNM": "Hold_StrikeDamage",
      "CIKHACMMGOL": {
        "MIJEEBIEOCG": "%4"
      },
      "BBIKFMELLKH": {
        "MIJEEBIEOCG": 0
      }
    },
    {
      "abilityName": "Avatar_Sayu_ElementalArt_Hold",
      "IIKDOHHIDNM": "Hold_Mix_StrikeDamage",
      "CIKHACMMGOL": {
        "MIJEEBIEOCG": "%5"
      },
      "BBIKFMELLKH": {
        "MIJEEBIEOCG": 0
      }
    }
  ],
  "Sayu_SkillUpgrade_3": [
    {
      "abilityName": "Avatar_Sayu_ElementalBurst",
      "IIKDOHHIDNM": "Damage_Ratio",
      "CIKHACMMGOL": {
        "MIJEEBIEOCG": "%1"
      },
      "BBIKFMELLKH": {
        "MIJEEBIEOCG": 0
      }
    },
    {
      "abilityName": "Avatar_Sayu_ElementalBurst",
      "IIKDOHHIDNM": "Heal_BaseAmount",
      "CIKHACMMGOL": {
        "MIJEEBIEOCG": "%2"
      },
      "BBIKFMELLKH": {
        "MIJEEBIEOCG": 0
      }
    },
    {
      "abilityName": "Avatar_Sayu_ElementalBurst",
      "IIKDOHHIDNM": "Heal_AttackRatio",
      "CIKHACMMGOL": {
        "MIJEEBIEOCG": "%3"
      },
      "BBIKFMELLKH": {
        "MIJEEBIEOCG": 0
      }
    },
    {
      "abilityName": "Avatar_Sayu_ElementalBurst_Phantom",
      "IIKDOHHIDNM": "Damage_Ratio",
      "CIKHACMMGOL": {
        "MIJEEBIEOCG": "%4"
      },
      "BBIKFMELLKH": {
        "MIJEEBIEOCG": 0
      }
    },
    {
      "abilityName": "Avatar_Sayu_ElementalBurst_Phantom",
      "IIKDOHHIDNM": "Heal_BaseAmount",
      "CIKHACMMGOL": {
        "MIJEEBIEOCG": "%5"
      },
      "BBIKFMELLKH": {
        "MIJEEBIEOCG": 0
      }
    },
    {
      "abilityName": "Avatar_Sayu_ElementalBurst_Phantom",
      "IIKDOHHIDNM": "Heal_AttackRatio",
      "CIKHACMMGOL": {
        "MIJEEBIEOCG": "%6"
      },
      "BBIKFMELLKH": {
        "MIJEEBIEOCG": 0
      }
    }
  ],
  "Sayu_PermanentSkill_1": [
    {
      "abilityName": "Avatar_Sayu_PermanentSkill_1"
    },
    {
      "abilityName": "Avatar_Sayu_PermanentSkill_1",
      "IIKDOHHIDNM": "Heal_BaseAmount",
      "CIKHACMMGOL": {
        "MIJEEBIEOCG": "%1"
      },
      "BBIKFMELLKH": {
        "MIJEEBIEOCG": 0
      }
    },
    {
      "abilityName": "Avatar_Sayu_PermanentSkill_1",
      "IIKDOHHIDNM": "Heal_MasteryRatio",
      "CIKHACMMGOL": {
        "MIJEEBIEOCG": "%2"
      },
      "BBIKFMELLKH": {
        "MIJEEBIEOCG": 0
      }
    },
    {
      "abilityName": "Avatar_Sayu_PermanentSkill_1",
      "IIKDOHHIDNM": "CDTime",
      "CIKHACMMGOL": {
        "MIJEEBIEOCG": "%3"
      },
      "BBIKFMELLKH": {
        "MIJEEBIEOCG": 0
      }
    }
  ],
  "Sayu_PermanentSkill_2": [
    {
      "abilityName": "Avatar_Sayu_ElementalBurst_Phantom",
      "EDPOLNJAJKB": "Sayu_PermanentSkill_2"
    },
    {
      "abilityName": "Avatar_Sayu_ElementalBurst_Phantom",
      "IIKDOHHIDNM": "PermanentSkill_2_RangeRatio",
      "CIKHACMMGOL": {
        "MIJEEBIEOCG": "%1"
      },
      "BBIKFMELLKH": {
        "MIJEEBIEOCG": 0
      }
    }
  ],
  "Sayu_Constellation_1": [
    {
      "abilityName": "Avatar_Sayu_ElementalBurst_Phantom",
      "EDPOLNJAJKB": "Sayu_Constellation_1"
    }
  ],
  "Sayu_Constellation_2": [
    {
      "abilityName": "Avatar_Sayu_Constellation_2"
    },
    {
      "abilityName": "Avatar_Sayu_Constellation_2",
      "IIKDOHHIDNM": "Rate",
      "CIKHACMMGOL": {
        "MIJEEBIEOCG": "%1"
      },
      "BBIKFMELLKH": {
        "MIJEEBIEOCG": 0
      }
    },
    {
      "abilityName": "Avatar_Sayu_Constellation_2",
      "IIKDOHHIDNM": "MaxLevel",
      "CIKHACMMGOL": {
        "MIJEEBIEOCG": "%2"
      },
      "BBIKFMELLKH": {
        "MIJEEBIEOCG": 0
      }
    }
  ],
  "Sayu_Constellation_3": [
    {
      "HMFINFAPKEF": "AvatarSkill",
      "PJEOFMCGJAJ": 9,
      "MCIPOFOCGNA": 3
    }
  ],
  "Sayu_Constellation_4": [
    {
      "abilityName": "Avatar_Sayu_Constellation_4"
    },
    {
      "abilityName": "Avatar_Sayu_Constellation_4",
      "IIKDOHHIDNM": "Energy",
      "CIKHACMMGOL": {
        "MIJEEBIEOCG": "%1"
      },
      "BBIKFMELLKH": {
        "MIJEEBIEOCG": 0
      }
    },
    {
      "abilityName": "Avatar_Sayu_Constellation_4",
      "IIKDOHHIDNM": "CDTime",
      "CIKHACMMGOL": {
        "MIJEEBIEOCG": "%2"
      },
      "BBIKFMELLKH": {
        "MIJEEBIEOCG": 0
      }
    }
  ],
  "Sayu_Constellation_5": [
    {
      "HMFINFAPKEF": "AvatarSkill",
      "PJEOFMCGJAJ": 2,
      "MCIPOFOCGNA": 3
    }
  ],
  "Sayu_Constellation_6": [
    {
      "abilityName": "Avatar_Sayu_ElementalBurst_Phantom",
      "EDPOLNJAJKB": "Sayu_Constellation_6"
    },
    {
      "abilityName": "Avatar_Sayu_ElementalBurst_Phantom",
      "IIKDOHHIDNM": "Constellation_6_PerMasteryDamage",
      "CIKHACMMGOL": {
        "MIJEEBIEOCG": "%1"
      },
      "BBIKFMELLKH": {
        "MIJEEBIEOCG": 0
      }
    },
    {
      "abilityName": "Avatar_Sayu_ElementalBurst_Phantom",
      "IIKDOHHIDNM": "Constellation_6_MaxDamage",
      "CIKHACMMGOL": {
        "MIJEEBIEOCG": "%2"
      },
      "BBIKFMELLKH": {
        "MIJEEBIEOCG": 0
      }
    },
    {
      "abilityName": "Avatar_Sayu_ElementalBurst_Phantom",
      "IIKDOHHIDNM": "Constellation_6_PerMasteryHeal",
      "CIKHACMMGOL": {
        "MIJEEBIEOCG": "%3"
      },
      "BBIKFMELLKH": {
        "MIJEEBIEOCG": 0
      }
    },
    {
      "abilityName": "Avatar_Sayu_ElementalBurst_Phantom",
      "IIKDOHHIDNM": "Constellation_6_MaxHeal",
      "CIKHACMMGOL": {
        "MIJEEBIEOCG": "%4"
      },
      "BBIKFMELLKH": {
        "MIJEEBIEOCG": 0
      }
    }
  ],
  "Sayu_ProudSkill_NonCombat_1": [
    {
      "abilityName": "Avatar_Sayu_Talent_Stealth_Animal_Misc"
    }
  ]
}