{
  "Mona_Talent_01": [
    {
      "abilityName": "Avatar_Mona_StarChart",
      "EDPOLNJAJKB": "Avatar_Mona_Talent_Talent_StarChart_ElementReactionUp"
    },
    {
      "abilityName": "Avatar_Mona_StarChart",
      "IIKDOHHIDNM": "AS_Mona_Talent_ElementReactionUp_Electric",
      "CIKHACMMGOL": {
        "MIJEEBIEOCG": "%1"
      },
      "BBIKFMELLKH": {
        "MIJEEBIEOCG": {}
      }
    },
    {
      "abilityName": "Avatar_Mona_StarChart",
      "IIKDOHHIDNM": "AS_Mona_Talent_ElementReactionUp_Steam",
      "CIKHACMMGOL": {
        "MIJEEBIEOCG": "%2"
      },
      "BBIKFMELLKH": {
        "MIJEEBIEOCG": {}
      }
    },
    {
      "abilityName": "Avatar_Mona_StarChart",
      "IIKDOHHIDNM": "AS_Mona_Talent_ElementReactionUp_SwirlWater",
      "CIKHACMMGOL": {
        "MIJEEBIEOCG": "%3"
      },
      "BBIKFMELLKH": {
        "MIJEEBIEOCG": {}
      }
    },
    {
      "abilityName": "Avatar_Mona_StarChart",
      "IIKDOHHIDNM": "AS_Mona_Talent_ElementReactionUp_Freeze",
      "CIKHACMMGOL": {
        "MIJEEBIEOCG": "%4"
      },
      "BBIKFMELLKH": {
        "MIJEEBIEOCG": {}
      }
    },
    {
      "abilityName": "Avatar_Mona_StarChart",
      "IIKDOHHIDNM": "AS_Mona_Talent_ElementReactionUp_Time",
      "CIKHACMMGOL": {
        "MIJEEBIEOCG": "%6"
      },
      "BBIKFMELLKH": {
        "MIJEEBIEOCG": {}
      }
    }
  ],
  "Mona_Talent_02": [
    {
      "abilityName": "Avatar_Mona_Talent_AutoExtraAttack"
    },
    {
      "abilityName": "Avatar_Mona_Talent_AutoExtraAttack",
      "IIKDOHHIDNM": "AS_Mona_Talent_AutoExtraAttack_Rate",
      "CIKHACMMGOL": {
        "MIJEEBIEOCG": "%1"
      },
      "BBIKFMELLKH": {
        "MIJEEBIEOCG": {}
      }
    },
    {
      "abilityName": "Avatar_Mona_Talent_AutoExtraAttack",
      "IIKDOHHIDNM": "AS_Mona_Talent_AutoExtraAttack_DamageRate",
      "CIKHACMMGOL": {
        "MIJEEBIEOCG": "%2"
      },
      "BBIKFMELLKH": {
        "MIJEEBIEOCG": {}
      }
    },
    {
      "abilityName": "Avatar_Mona_Talent_AutoExtraAttack",
      "IIKDOHHIDNM": "AS_Mona_Talent_AutoExtraAttack_CD",
      "CIKHACMMGOL": {
        "MIJEEBIEOCG": "%3"
      },
      "BBIKFMELLKH": {
        "MIJEEBIEOCG": {}
      }
    }
  ],
  "Mona_Talent_03": [
    {
      "HMFINFAPKEF": "AvatarSkill",
      "PJEOFMCGJAJ": 9,
      "MCIPOFOCGNA": 3
    }
  ],
  "Mona_Talent_04": [
    {
      "abilityName": "Avatar_Mona_StarChart",
      "IIKDOHHIDNM": "AS_Mona_Talent_AntiCritical",
      "CIKHACMMGOL": {
        "MIJEEBIEOCG": "%1"
      },
      "BBIKFMELLKH": {
        "MIJEEBIEOCG": {}
      }
    }
  ],
  "Mona_Talent_05": [
    {
      "HMFINFAPKEF": "AvatarSkill",
      "PJEOFMCGJAJ": 2,
      "MCIPOFOCGNA": 3
    }
  ],
  "Mona_Talent_06": [
    {
      "abilityName": "Avatar_Mona_Talent_LiquidStrike_ExtraAttakDamageUp"
    },
    {
      "abilityName": "Avatar_Mona_Talent_LiquidStrike_ExtraAttakDamageUp",
      "IIKDOHHIDNM": "AS_Mona_Talent_LiquidStrike_ExtraAttackDamageUp_ThinkTime",
      "CIKHACMMGOL": {
        "MIJEEBIEOCG": "%1"
      },
      "BBIKFMELLKH": {
        "MIJEEBIEOCG": {}
      }
    },
    {
      "abilityName": "Avatar_Mona_Talent_LiquidStrike_ExtraAttakDamageUp",
      "IIKDOHHIDNM": "AS_Mona_Talent_LiquidStrike_ExtraAttackDamageUp_ThinkValue",
      "CIKHACMMGOL": {
        "MIJEEBIEOCG": "%2"
      },
      "BBIKFMELLKH": {
        "MIJEEBIEOCG": {}
      }
    },
    {
      "abilityName": "Avatar_Mona_Talent_LiquidStrike_ExtraAttakDamageUp",
      "IIKDOHHIDNM": "AS_Mona_Talent_LiquidStrike_ExtraAttackDamageUp_MaxValue",
      "CIKHACMMGOL": {
        "MIJEEBIEOCG": "%3"
      },
      "BBIKFMELLKH": {
        "MIJEEBIEOCG": {}
      }
    },
    {
      "abilityName": "Avatar_Mona_Talent_LiquidStrike_ExtraAttakDamageUp",
      "IIKDOHHIDNM": "AS_Mona_Talent_LiquidStrike_ExtraAttackDamageUp_Time",
      "CIKHACMMGOL": {
        "MIJEEBIEOCG": "%4"
      },
      "BBIKFMELLKH": {
        "MIJEEBIEOCG": {}
      }
    }
  ],
  "Mona_PermanentSkill_01": [
    {
      "abilityName": "Avatar_Mona_Talent_LiquidStriket_Phantom"
    },
    {
      "abilityName": "Avatar_Mona_Talent_LiquidStriket_Phantom",
      "IIKDOHHIDNM": "AS_Mona_Talent_LiquidStrike_LiquidPhantom_Timer",
      "CIKHACMMGOL": {
        "MIJEEBIEOCG": "%1"
      },
      "BBIKFMELLKH": {
        "MIJEEBIEOCG": {}
      }
    },
    {
      "abilityName": "Avatar_Mona_Talent_MonaGadgetSkill_LiquidPhantom",
      "IIKDOHHIDNM": "AS_Mona_Talent_LiquidStrike_LiquidPhantom_Duration",
      "CIKHACMMGOL": {
        "MIJEEBIEOCG": "%2"
      },
      "BBIKFMELLKH": {
        "MIJEEBIEOCG": {}
      }
    },
    {
      "abilityName": "Avatar_Mona_Talent_MonaGadgetSkill_LiquidPhantom",
      "IIKDOHHIDNM": "AS_Mona_Talent_LiquidStrike_LiquidPhantom_DamageRate",
      "CIKHACMMGOL": {
        "MIJEEBIEOCG": "%3"
      },
      "BBIKFMELLKH": {
        "MIJEEBIEOCG": {}
      }
    }
  ],
  "Mona_PermanentSkill_02": [
    {
      "abilityName": "Avatar_Mona_Talent_ChargeEfficiencyToWaterAddHurt"
    },
    {
      "abilityName": "Avatar_Mona_Talent_ChargeEfficiencyToWaterAddHurt",
      "IIKDOHHIDNM": "AS_Mona_Talent_WaterHurtAddRate",
      "CIKHACMMGOL": {
        "MIJEEBIEOCG": "%2"
      },
      "BBIKFMELLKH": {
        "MIJEEBIEOCG": {}
      }
    }
  ],
  "Mona_SkillUpgrade_01": [
    {
      "abilityName": "Avatar_Mona_NormalAttack_01",
      "IIKDOHHIDNM": "AS_Mona_NormalAttack_01",
      "CIKHACMMGOL": {
        "MIJEEBIEOCG": "%1"
      },
      "BBIKFMELLKH": {
        "MIJEEBIEOCG": {}
      }
    },
    {
      "abilityName": "Avatar_Mona_NormalAttack_02",
      "IIKDOHHIDNM": "AS_Mona_NormalAttack_02",
      "CIKHACMMGOL": {
        "MIJEEBIEOCG": "%2"
      },
      "BBIKFMELLKH": {
        "MIJEEBIEOCG": {}
      }
    },
    {
      "abilityName": "Avatar_Mona_NormalAttack_03",
      "IIKDOHHIDNM": "AS_Mona_NormalAttack_03",
      "CIKHACMMGOL": {
        "MIJEEBIEOCG": "%3"
      },
      "BBIKFMELLKH": {
        "MIJEEBIEOCG": {}
      }
    },
    {
      "abilityName": "Avatar_Mona_NormalAttack_04_Hit",
      "IIKDOHHIDNM": "AS_Mona_NormalAttack_04",
      "CIKHACMMGOL": {
        "MIJEEBIEOCG": "%4"
      },
      "BBIKFMELLKH": {
        "MIJEEBIEOCG": {}
      }
    },
    {
      "abilityName": "Avatar_Mona_ExtraAttack_Damage",
      "IIKDOHHIDNM": "AS_Mona_ExtraAttack_Damge",
      "CIKHACMMGOL": {
        "MIJEEBIEOCG": "%5"
      },
      "BBIKFMELLKH": {
        "MIJEEBIEOCG": {}
      }
    },
    {
      "abilityName": "Avatar_Mona_ExtraAttack",
      "IIKDOHHIDNM": "ExtraAttack_Catalyst_Stamina_Cost",
      "CIKHACMMGOL": {
        "MIJEEBIEOCG": "%6"
      },
      "BBIKFMELLKH": {
        "MIJEEBIEOCG": {}
      }
    },
    {
      "abilityName": "Avatar_Mona_FallingAnthem",
      "IIKDOHHIDNM": "FallingAnthem_Normal_Loop_Damage",
      "CIKHACMMGOL": {
        "MIJEEBIEOCG": "%7"
      },
      "BBIKFMELLKH": {
        "MIJEEBIEOCG": {}
      }
    },
    {
      "abilityName": "Avatar_Mona_FallingAnthem",
      "IIKDOHHIDNM": "FallingAnthem_Normal_Rank_1_Damage",
      "CIKHACMMGOL": {
        "MIJEEBIEOCG": "%8"
      },
      "BBIKFMELLKH": {
        "MIJEEBIEOCG": {}
      }
    },
    {
      "abilityName": "Avatar_Mona_FallingAnthem",
      "IIKDOHHIDNM": "FallingAnthem_Normal_Rank_2_Damage",
      "CIKHACMMGOL": {
        "MIJEEBIEOCG": "%9"
      },
      "BBIKFMELLKH": {
        "MIJEEBIEOCG": {}
      }
    },
    {
      "abilityName": "Avatar_Mona_Talent_AutoExtraAttack",
      "IIKDOHHIDNM": "AS_Mona_ExtraAttack_Damge",
      "CIKHACMMGOL": {
        "MIJEEBIEOCG": "%5"
      },
      "BBIKFMELLKH": {
        "MIJEEBIEOCG": {}
      }
    }
  ],
  "Mona_SkillUpgrade_02": [
    {
      "abilityName": "Avatar_MonaGadgetSkill_Phantom",
      "IIKDOHHIDNM": "AS_Mona_Phantom_ThinkDamageRate",
      "CIKHACMMGOL": {
        "MIJEEBIEOCG": "%1"
      },
      "BBIKFMELLKH": {
        "MIJEEBIEOCG": {}
      }
    },
    {
      "abilityName": "Avatar_MonaGadgetSkill_PhantomLastAttack",
      "IIKDOHHIDNM": "AS_Mona_Phantom_LastDamageRate",
      "CIKHACMMGOL": {
        "MIJEEBIEOCG": "%2"
      },
      "BBIKFMELLKH": {
        "MIJEEBIEOCG": {}
      }
    },
    {
      "abilityName": "Avatar_Mona_Talent_MonaGadgetSkill_LiquidPhantom",
      "IIKDOHHIDNM": "AS_Mona_Phantom_LastDamageRate",
      "CIKHACMMGOL": {
        "MIJEEBIEOCG": "%2"
      },
      "BBIKFMELLKH": {
        "MIJEEBIEOCG": {}
      }
    }
  ],
  "Mona_SkillUpgrade_03": [
    {
      "abilityName": "Avatar_Mona_StarChart",
      "IIKDOHHIDNM": "AS_Mona_StarChart_Bubble_Duration",
      "CIKHACMMGOL": {
        "MIJEEBIEOCG": "%1"
      },
      "BBIKFMELLKH": {
        "MIJEEBIEOCG": {}
      }
    },
    {
      "abilityName": "Avatar_Mona_StarChart",
      "IIKDOHHIDNM": "AS_Mona_StarChart_Bubble_RemovedDamage",
      "CIKHACMMGOL": {
        "MIJEEBIEOCG": "%2"
      },
      "BBIKFMELLKH": {
        "MIJEEBIEOCG": {}
      }
    },
    {
      "abilityName": "Avatar_Mona_StarChart",
      "IIKDOHHIDNM": "AS_Mona_StarChart_HurtUp_DamageRate",
      "CIKHACMMGOL": {
        "MIJEEBIEOCG": "%3"
      },
      "BBIKFMELLKH": {
        "MIJEEBIEOCG": {}
      }
    },
    {
      "abilityName": "Avatar_Mona_StarChart",
      "IIKDOHHIDNM": "AS_Mona_StarChart_RemovedDamage_HurtUp_DamageRate",
      "CIKHACMMGOL": {
        "MIJEEBIEOCG": "%3"
      },
      "BBIKFMELLKH": {
        "MIJEEBIEOCG": {}
      }
    },
    {
      "abilityName": "Avatar_Mona_StarChart",
      "IIKDOHHIDNM": "AS_Mona_StarChart_HurtUp_Duration",
      "CIKHACMMGOL": {
        "MIJEEBIEOCG": "%4"
      },
      "BBIKFMELLKH": {
        "MIJEEBIEOCG": {}
      }
    }
  ],
  "Mona_SkillUpgrade_04": [
    {
      "abilityName": "Avatar_Mona_Liquid_TriggerAbility",
      "IIKDOHHIDNM": "StaminaStartCost",
      "CIKHACMMGOL": {
        "MIJEEBIEOCG": "%1"
      },
      "BBIKFMELLKH": {
        "MIJEEBIEOCG": 0
      }
    },
    {
      "abilityName": "Avatar_Mona_LiquidStrike",
      "IIKDOHHIDNM": "StaminaCost",
      "CIKHACMMGOL": {
        "MIJEEBIEOCG": "%2"
      },
      "BBIKFMELLKH": {
        "MIJEEBIEOCG": 0
      }
    }
  ]
}